rest_process/__init__.py
rest_process/server.py
rest_process/start.py
rest_process/tests.py
rest_process/processes/__init__.py
rest_process/processes/grow.py
rest_process-1.0.1.dist-info/METADATA
rest_process-1.0.1.dist-info/WHEEL
rest_process-1.0.1.dist-info/top_level.txt
rest_process-1.0.1.dist-info/RECORD
