Metadata-Version: 2.4
Name: rest-process
Version: 1.0.1
Summary: server for hosting processes and composites from process-bigraph
Requires-Python: >=3.11
Requires-Dist: fastapi>=0.116.1
Requires-Dist: fastapi-utils>=0.8.0
Requires-Dist: typing-inspect>=0.9.0
Requires-Dist: uvicorn>=0.35.0
Requires-Dist: process-bigraph
